[{"timestamp":1596412464717,"files":[{"filename":"test1/index.js","previous":62906,"size":62759,"diff":-147},{"filename":"test2/index.js","previous":62819,"size":62742,"diff":-77}]},{"timestamp":1596410440476,"files":[{"filename":"test1/index.js","previous":62889,"size":62906,"diff":17},{"filename":"test2/index.js","previous":62819,"size":62819,"diff":0}]},{"timestamp":1596405953164,"files":[{"filename":"test1/index.js","previous":63242,"size":62889,"diff":-353},{"filename":"test2/index.js","previous":63175,"size":62819,"diff":-356}]},{"timestamp":1596405729176,"files":[{"filename":"test1/index.js","previous":24741,"size":63242,"diff":38501},{"filename":"test2/index.js","previous":24783,"size":63175,"diff":38392}]},{"timestamp":1596393668388,"files":[{"filename":"test1/index.js","previous":1248,"size":24741,"diff":23493},{"filename":"test2/index.js","previous":1292,"size":24783,"diff":23491}]}]
